metamaker/__init__.py
metamaker/__main__.py
metamaker/api.py
metamaker/aws.py
metamaker/commands/__init__.py
metamaker/commands/build.py
metamaker/commands/run/__init__.py
metamaker/commands/run/run.py
metamaker/commands/run/serve.py
metamaker/commands/run/train.py
metamaker/commands/sagemaker/__init__.py
metamaker/commands/sagemaker/deploy.py
metamaker/commands/sagemaker/sagemaker.py
metamaker/commands/sagemaker/train.py
metamaker/commands/subcommand.py
metamaker/config.py
metamaker/docker.py
metamaker/hyperparameter.py
metamaker/metamaker.py
metamaker/poetry.py
metamaker/py.typed
metamaker-0.1.0.dist-info/entry_points.txt
metamaker-0.1.0.dist-info/LICENSE
metamaker-0.1.0.dist-info/WHEEL
metamaker-0.1.0.dist-info/METADATA
metamaker-0.1.0.dist-info/RECORD
