Metadata-Version: 2.1
Name: metamaker
Version: 0.1.0
Summary: Simple CLI to train and deploy your ML models with AWS SageMaker
Home-page: https://github.com/altescy/metamaker
License: MIT
Keywords: python,machine-learning,sagemaker
Author: altescy
Author-email: altescy@fastmail.com
Requires-Python: >=3.8,<4.0
Classifier: License :: OSI Approved :: MIT License
Classifier: Programming Language :: Python :: 3
Classifier: Programming Language :: Python :: 3.10
Classifier: Programming Language :: Python :: 3.8
Classifier: Programming Language :: Python :: 3.9
Requires-Dist: boto3 (>=1.19.9,<2.0.0)
Requires-Dist: fastapi (>=0.70.0,<0.71.0)
Requires-Dist: pydantic (>=1.8.2,<2.0.0)
Requires-Dist: pyyaml (>=5.0,<6.0)
Requires-Dist: sagemaker[local] (>=2.68.0,<3.0.0)
Requires-Dist: uvicorn (>=0.15.0,<0.16.0)
